fastapi_versioner/__init__.py
fastapi_versioner/compatibility/__init__.py
fastapi_versioner/core/__init__.py
fastapi_versioner/core/route_collector.py
fastapi_versioner/core/version_manager.py
fastapi_versioner/core/versioned_app.py
fastapi_versioner/decorators/__init__.py
fastapi_versioner/decorators/deprecated.py
fastapi_versioner/decorators/version.py
fastapi_versioner/deprecation/__init__.py
fastapi_versioner/documentation/__init__.py
fastapi_versioner/exceptions/__init__.py
fastapi_versioner/exceptions/base.py
fastapi_versioner/exceptions/versioning.py
fastapi_versioner/middleware/__init__.py
fastapi_versioner/strategies/__init__.py
fastapi_versioner/strategies/base.py
fastapi_versioner/strategies/header.py
fastapi_versioner/strategies/query_param.py
fastapi_versioner/strategies/url_path.py
fastapi_versioner/testing/__init__.py
fastapi_versioner/types/__init__.py
fastapi_versioner/types/compatibility.py
fastapi_versioner/types/config.py
fastapi_versioner/types/deprecation.py
fastapi_versioner/types/version.py
fastapi_versioner/utils/__init__.py
fastapi_versioner-0.1.0.dist-info/METADATA
fastapi_versioner-0.1.0.dist-info/WHEEL
fastapi_versioner-0.1.0.dist-info/RECORD
