Metadata-Version: 2.4
Name: fastapi-versioner
Version: 0.1.0
Summary: Production-ready FastAPI versioning library with comprehensive deprecation management and backward compatibility
Project-URL: Homepage, https://github.com/tonlls/fastapi-versioner
Project-URL: Repository, https://github.com/tonlls/fastapi-versioner
Project-URL: Documentation, https://github.com/tonlls/fastapi-versioner
Project-URL: Issues, https://github.com/tonlls/fastapi-versioner/issues
Author-email: Ton Llucia <tonlls1999@gmail.com>
License: MIT
Requires-Python: >=3.12
Requires-Dist: fastapi>=0.115.12
Requires-Dist: pydantic>=2.11.5
